yc_central/__init__.py
yc_central/analysis.py
yc_central/constants.py
yc_central/historical.py
yc_central-0.0.1.dist-info/METADATA
yc_central-0.0.1.dist-info/WHEEL
yc_central-0.0.1.dist-info/top_level.txt
yc_central-0.0.1.dist-info/RECORD
