Metadata-Version: 2.1
Name: yc-central
Version: 0.0.1
Summary: My package description
Author-email: "<your name>" <some-email@gmail.com>
License: MIT
Keywords: one,two
Classifier: Programming Language :: Python :: 3
Requires-Python: >=3.7
Provides-Extra: dev
Requires-Dist: yc-pypi[release,static-code-qa,test]; extra == "dev"
Provides-Extra: release
Requires-Dist: build; extra == "release"
Requires-Dist: twine; extra == "release"
Provides-Extra: static-code-qa
Requires-Dist: pre-commit; extra == "static-code-qa"
Requires-Dist: pylint; extra == "static-code-qa"
Requires-Dist: black; extra == "static-code-qa"
Requires-Dist: isort; extra == "static-code-qa"
Requires-Dist: flake8; extra == "static-code-qa"
Requires-Dist: flake8-docstrings; extra == "static-code-qa"
Requires-Dist: Flake8-pyproject; extra == "static-code-qa"
Requires-Dist: radon; extra == "static-code-qa"
Provides-Extra: test
Requires-Dist: pytest; extra == "test"
Requires-Dist: pytest-cov; extra == "test"
